openinstruct/__init__.py
openinstruct/client.py
openinstruct/context.py
openinstruct/extraction.py
openinstruct/prompts.py
openinstruct/py.typed
openinstruct/retry.py
openinstruct/schema.py
openinstruct/types.py
openinstruct/providers/__init__.py
openinstruct/providers/anthropic_provider.py
openinstruct/providers/base.py
openinstruct/providers/google_provider.py
openinstruct/providers/openai_provider.py
openinstruct-1.1.0.dist-info/METADATA
openinstruct-1.1.0.dist-info/WHEEL
openinstruct-1.1.0.dist-info/licenses/LICENSE
openinstruct-1.1.0.dist-info/RECORD
