Metadata-Version: 2.4
Name: openinstruct
Version: 1.1.0
Summary: Structured outputs for LLMs with 30-70% token savings using TSON optimization
Project-URL: Homepage, https://github.com/zenoaihq/openinstruct
Project-URL: Repository, https://github.com/zenoaihq/openinstruct
Project-URL: Documentation, https://github.com/zenoaihq/openinstruct#readme
Project-URL: Issues, https://github.com/zenoaihq/openinstruct/issues
Author-email: Zeno AI <contact@zenoai.tech>
License-Expression: MIT
License-File: LICENSE
Keywords: anthropic,extraction,gemini,llm,openai,pydantic,structured-output,token-efficient,tson
Classifier: Development Status :: 4 - Beta
Classifier: Intended Audience :: Developers
Classifier: License :: OSI Approved :: MIT License
Classifier: Operating System :: OS Independent
Classifier: Programming Language :: Python :: 3
Classifier: Programming Language :: Python :: 3.9
Classifier: Programming Language :: Python :: 3.10
Classifier: Programming Language :: Python :: 3.11
Classifier: Programming Language :: Python :: 3.12
Classifier: Topic :: Scientific/Engineering :: Artificial Intelligence
Classifier: Topic :: Software Development :: Libraries :: Python Modules
Classifier: Typing :: Typed
Requires-Python: >=3.9
Requires-Dist: httpx>=0.25.0
Requires-Dist: pydantic>=2.0
Requires-Dist: tson>=1.0.0
Provides-Extra: dev
Requires-Dist: mypy>=1.0; extra == 'dev'
Requires-Dist: pytest-asyncio>=0.21; extra == 'dev'
Requires-Dist: pytest>=7.0; extra == 'dev'
Requires-Dist: ruff>=0.1; extra == 'dev'
